MANIFEST.in
README.md
VERSION.txt
requirements.txt
setup.py
geolite2utils/__init__.py
geolite2utils.egg-info/PKG-INFO
geolite2utils.egg-info/SOURCES.txt
geolite2utils.egg-info/dependency_links.txt
geolite2utils.egg-info/not-zip-safe
geolite2utils.egg-info/requires.txt
geolite2utils.egg-info/top_level.txt