Metadata-Version: 1.0
Name: geolite2utils
Version: 1.0.4
Summary: Download, extract, and use MaxMind GeoLite2 databases from Python.
Home-page: https://github.com/matix-io/python-geolite2utils
Author: Connor Bode
Author-email: connor@matix.io
License: MIT
Platform: UNKNOWN
